LICENSE
MANIFEST.in
README.md
package.json
setup.py
dash_express_components/AggrTransform.py
dash_express_components/AsType.py
dash_express_components/Bar.py
dash_express_components/BarCount.py
dash_express_components/Base.py
dash_express_components/BinTransform.py
dash_express_components/Box.py
dash_express_components/CategoryLookup.py
dash_express_components/CombinecatTransform.py
dash_express_components/ConfigReceiver.py
dash_express_components/Configurator.py
dash_express_components/CoreGraph.py
dash_express_components/DataGraph.py
dash_express_components/DropnaTransform.py
dash_express_components/EvalTransform.py
dash_express_components/Filter.py
dash_express_components/FilterIqrTransform.py
dash_express_components/Graph.py
dash_express_components/GroupedSample.py
dash_express_components/HistogramLine.py
dash_express_components/Imshow.py
dash_express_components/Localstore.py
dash_express_components/MeltTransform.py
dash_express_components/MetaCheck.py
dash_express_components/Parameterize.py
dash_express_components/PivotTableTransform.py
dash_express_components/Plotter.py
dash_express_components/PlotterBase.py
dash_express_components/Polygon.py
dash_express_components/Probability.py
dash_express_components/RenameTransform.py
dash_express_components/RequestStore.py
dash_express_components/Scatter.py
dash_express_components/ScatterMatrix.py
dash_express_components/StrSplitTransform.py
dash_express_components/SubComponentBase.py
dash_express_components/Table.py
dash_express_components/Transform.py
dash_express_components/Violin.py
dash_express_components/WideToLong.py
dash_express_components/ZerosToNanTransform.py
dash_express_components/__init__.py
dash_express_components/_imports_.py
dash_express_components/async-excel.js
dash_express_components/async-excel.js.map
dash_express_components/dash_express_components.min.js
dash_express_components/dash_express_components.min.js.map
dash_express_components/metadata.json
dash_express_components/package-info.json
dash_express_components.egg-info/PKG-INFO
dash_express_components.egg-info/SOURCES.txt
dash_express_components.egg-info/dependency_links.txt
dash_express_components.egg-info/requires.txt
dash_express_components.egg-info/top_level.txt
