Metadata-Version: 2.1
Name: dash-express-components
Version: 0.0.111
Summary: Simple widgets to add plotly express style plotting to dash
Home-page: https://github.com/VK/dash-express-components
Author: Viktor Krückl <viktor@krueckl.de>
License: MIT
Classifier: Framework :: Dash
License-File: LICENSE
